search_space/__init__.py
python_search_space-1.0.1.dist-info/LICENSE
python_search_space-1.0.1.dist-info/METADATA
python_search_space-1.0.1.dist-info/WHEEL
python_search_space-1.0.1.dist-info/top_level.txt
python_search_space-1.0.1.dist-info/RECORD
