Metadata-Version: 2.1
Name: python-search-space
Version: 1.0.1
Summary: Python's DSL to describe the search space of search problems
Author-email: Daniel Orlando Ortiz Pacheco <danielorlandoortizpacheco@gmial.com>
License: MIT License
Project-URL: Homepage, https://github.com/danielorlando97/search-space
Keywords: describe,problems,space,search
Classifier: License :: OSI Approved :: MIT License
Classifier: Programming Language :: Python
Classifier: Programming Language :: Python :: 3
Classifier: Development Status :: 5 - Production/Stable
Classifier: Topic :: Scientific/Engineering
Classifier: Topic :: Scientific/Engineering :: Artificial Intelligence
Requires-Python: >=3.9
License-File: LICENSE
Requires-Dist: typing-extensions (==4.4.0)
Provides-Extra: dev
Requires-Dist: ipykernel ; extra == 'dev'
Requires-Dist: autopep8 ; extra == 'dev'
Requires-Dist: pytest (==7.1.2) ; extra == 'dev'
Requires-Dist: matplotlib (==3.5.3) ; extra == 'dev'
Requires-Dist: pandas (==1.5.1) ; extra == 'dev'
